HtmlBaodianWaiBowang/README.md
HtmlBaodianWaiBowang/__init__.py
HtmlBaodianWaiBowang/__main__.py
HtmlBaodianWaiBowang/file.epub
HtmlBaodianWaiBowang/index.html
HtmlBaodianWaiBowang/css/__init__.py
HtmlBaodianWaiBowang/css/annotations.css
HtmlBaodianWaiBowang/css/main.css
HtmlBaodianWaiBowang/css/normalize.css
HtmlBaodianWaiBowang/css/popup.css
HtmlBaodianWaiBowang/font/__init__.py
HtmlBaodianWaiBowang/font/fontello.eot
HtmlBaodianWaiBowang/font/fontello.svg
HtmlBaodianWaiBowang/font/fontello.ttf
HtmlBaodianWaiBowang/font/fontello.woff
HtmlBaodianWaiBowang/img/__init__.py
HtmlBaodianWaiBowang/img/annotator-glyph-sprite.png
HtmlBaodianWaiBowang/img/annotator-icon-sprite.png
HtmlBaodianWaiBowang/img/apple-touch-icon.png
HtmlBaodianWaiBowang/img/cancelfullscreen.png
HtmlBaodianWaiBowang/img/close.png
HtmlBaodianWaiBowang/img/fullscreen.png
HtmlBaodianWaiBowang/img/loader.gif
HtmlBaodianWaiBowang/img/menu-icon.png
HtmlBaodianWaiBowang/img/save.png
HtmlBaodianWaiBowang/img/saved.png
HtmlBaodianWaiBowang/img/settings-s.png
HtmlBaodianWaiBowang/img/settings.png
HtmlBaodianWaiBowang/img/star.png
HtmlBaodianWaiBowang/js/__init__.py
HtmlBaodianWaiBowang/js/epub.js
HtmlBaodianWaiBowang/js/epub.min.js
HtmlBaodianWaiBowang/js/epub.min.map
HtmlBaodianWaiBowang/js/hooks.min.js
HtmlBaodianWaiBowang/js/hooks.min.map
HtmlBaodianWaiBowang/js/reader.js
HtmlBaodianWaiBowang/js/reader.js.map
HtmlBaodianWaiBowang/js/reader.min.js
HtmlBaodianWaiBowang/js/reader.min.map
HtmlBaodianWaiBowang/js/hooks/__init__.py
HtmlBaodianWaiBowang/js/hooks/extensions/__init__.py
HtmlBaodianWaiBowang/js/hooks/extensions/highlight.js
HtmlBaodianWaiBowang/js/libs/__init__.py
HtmlBaodianWaiBowang/js/libs/jquery.min.js
HtmlBaodianWaiBowang/js/libs/localforage.min.js
HtmlBaodianWaiBowang/js/libs/screenfull.js
HtmlBaodianWaiBowang/js/libs/screenfull.min.js
HtmlBaodianWaiBowang/js/libs/zip.min.js
HtmlBaodianWaiBowang/js/plugins/__init__.py
HtmlBaodianWaiBowang/js/plugins/hypothesis.js
html_baodian_wai_bowang-2024.3.4.0.dist-info/METADATA
html_baodian_wai_bowang-2024.3.4.0.dist-info/WHEEL
html_baodian_wai_bowang-2024.3.4.0.dist-info/entry_points.txt
html_baodian_wai_bowang-2024.3.4.0.dist-info/top_level.txt
html_baodian_wai_bowang-2024.3.4.0.dist-info/RECORD
